filecomp/__init__.py
filecomp/filecomp.py
filecomp-0.0.3.dist-info/License.txt
filecomp-0.0.3.dist-info/METADATA
filecomp-0.0.3.dist-info/WHEEL
filecomp-0.0.3.dist-info/top_level.txt
filecomp-0.0.3.dist-info/RECORD
