Metadata-Version: 2.1
Name: filecomp
Version: 0.0.3
Summary: Function that finds maximal and minimal sized contents of a directory
Home-page: UNKNOWN
Author: Veefencer
Author-email: daredevill2912@gmail.com
License: UNKNOWN
Platform: UNKNOWN
Classifier: Programming Language :: Python :: 3
Classifier: Operating System :: Microsoft :: Windows
Requires-Python: >=3.7
License-File: License.txt
